Metadata-Version: 1.2
Name: PTableUnicode
Version: 0.9.3
Summary: A simple Python library for easily displaying tabular data in a visually appealing ASCII table format
Home-page: https://github.com/tducret/PTable
Author: Luke Maurits
Author-email: luke@maurits.id.au
Maintainer: Kane Blueriver
Maintainer-email: kxxoling@gmail.com
License: BSD (3 clause)
Platform: UNKNOWN
Classifier: Programming Language :: Python
Classifier: Programming Language :: Python :: 2
Classifier: Programming Language :: Python :: 2.7
Classifier: Programming Language :: Python :: 3
Classifier: Programming Language :: Python :: 3.4
Classifier: Programming Language :: Python :: 3.5
Classifier: Programming Language :: Python :: 3.6
Classifier: Programming Language :: Python :: 3.7
Classifier: Programming Language :: Python :: Implementation :: CPython
Classifier: License :: OSI Approved :: BSD License
Classifier: Topic :: Text Processing
